morfosi/__init__.py
morfosi/lib.py
morfosi/registry.py
morfosi/schema.py
morfosi/tracing/__init__.py
morfosi/tracing/base.py
morfosi/tracing/class_tracer.py
morfosi/tracing/dict_tracer.py
morfosi/tracing/list_tracer.py
morfosi/tracing/snapshot.py
morfosi/tracing/trace.py
morfosi/tracing/utils.py
pymorfosi-1.0.2.dist-info/LICENSE
pymorfosi-1.0.2.dist-info/METADATA
pymorfosi-1.0.2.dist-info/WHEEL
pymorfosi-1.0.2.dist-info/top_level.txt
pymorfosi-1.0.2.dist-info/RECORD
