Metadata-Version: 2.1
Name: pymorfosi
Version: 1.0.2
Summary: An experimental library for mutation tracing in Python
Author-email: Federico Terzi <federicoterzi96@gmail.com>
License: MIT License
Project-URL: Homepage, https://github.com/federico-terzi/morfosi-python
Keywords: mutation,tracing,debug
Classifier: License :: OSI Approved :: MIT License
Classifier: Programming Language :: Python
Classifier: Programming Language :: Python :: 3
Requires-Python: >=3.8
License-File: LICENSE
Requires-Dist: wrapt (>=1.13.3)
Provides-Extra: dev
Requires-Dist: black ; extra == 'dev'
Requires-Dist: pytest ; extra == 'dev'
